<?xml version="1.0" encoding="UTF-8" standalone="yes"?>

<item>
<title>[COLOR blue]Dragon Ball Super - 1x01 - El precio de la paz mundial.¿Quién ganó los 100 millones?[/COLOR]</title>        
<urlsolve>https://openload.co/f/PBUxln9L2CE/DBS_1_kodiland.mkv.mp4</urlsolve>
<thumbnail></thumbnail>
<fanart></fanart>
</item>

<item>
<title>[COLOR blue]Dragon Ball Super - 1x02 - ¡Las vacaciones prometidas! ¡¿Vegeta va de vacaciones con su familia?![/COLOR]</title>        
<urlsolve>https://openload.co/f/pu6ipQoAgTQ/DBS_02_Kodiland.mkv.mp4</urlsolve>
<thumbnail></thumbnail>
<fanart></fanart>
</item>

<item>
<title>[COLOR blue]Dragon Ball Super - 1x03 - ¡¿Dónde está el resto de mi sueño?! ¡La búsqueda del Super Saiyajin Dios![/COLOR]</title>        
<urlsolve>https://openload.co/f/VfMssNGsTg4/DBS_03_kodiland.mkv.mp4</urlsolve>
<thumbnail></thumbnail>
<fanart></fanart>
</item>

<item>
<title>[COLOR blue]Dragon Ball Super - 1x04 - ¡Vayamos por las Bolas del Dragón! ¡La gran estrategia de la banda de Pilaf![/COLOR]</title>        
<urlsolve></urlsolve>
<thumbnail></thumbnail>
<fanart></fanart>
</item>

<item>
<title>[COLOR blue]Dragon Ball Super - 1x05 - ¡Batalla decisiva en el planeta Kaio! Goku vs Bills, el Dios de la Destrucción![/COLOR]</title>        
<urlsolve></urlsolve>
<thumbnail></thumbnail>
<fanart></fanart>
</item>

<item>
<title>[COLOR blue]Dragon Ball Super - 1x06 - No hagan enfadar al Dios de la destrucción. La emocionante fiesta de cumpleaños[/COLOR]</title>        
<urlsolve>https://openload.co/f/-aA8ex4ZwCc/DBS_06_kodiland.mkv.mp4</urlsolve>
<thumbnail></thumbnail>
<fanart></fanart>
</item>

<item>
<title>[COLOR blue]Dragon Ball Super - 1x07 - ¡Nadie toca a mi Bulma! ¡La ira de Vegeta estalla![/COLOR]</title>        
<urlsolve></urlsolve>
<thumbnail></thumbnail>
<fanart></fanart>
</item>

<item>
<title>[COLOR blue]Dragon Ball Super - 1x08 - ¡Goku llega! La última oportunidad de Bills[/COLOR]</title>        
<urlsolve></urlsolve>
<thumbnail></thumbnail>
<fanart></fanart>
</item>

<item>
<title>[COLOR blue]Dragon Ball Super - 1x09 - Disculpa la demora Bills. Finalmente nace el Dios Súper Saiyajin[/COLOR]</title>        
<urlsolve></urlsolve>
<thumbnail></thumbnail>
<fanart></fanart>
</item>

<item>
<title>[COLOR blue]Dragon Ball Super - 1x10 - ¡Muestranos tu fuerza Goku! ¡El poder del Dios Súper Saiyajin![/COLOR]</title>        
<urlsolve></urlsolve>
<thumbnail></thumbnail>
<fanart></fanart>
</item>

<item>
<title>[COLOR blue]Dragon Ball Super - 1x11 - ¡Sigamos adelante, gran Bills! La Batalla de los Dioses continúa[/COLOR]</title>        
<urlsolve></urlsolve>
<thumbnail></thumbnail>
<fanart></fanart>
</item>

<item>
<title>[COLOR blue]Dragon Ball Super - 1x12 - ¡El universo tiembla! ¡El Dios de la destrucción vs el Dios Súper Saiyajin![/COLOR]</title>        
<urlsolve></urlsolve>
<thumbnail></thumbnail>
<fanart></fanart>
</item>

<item>
<title>[COLOR blue]Dragon Ball Super - 1x13 - ¡Goku sobrepasa los poderes del Dios Súper Saiyain![/COLOR]</title>        
<urlsolve></urlsolve>
<thumbnail></thumbnail>
<fanart></fanart>
</item>

<item>
<title>[COLOR blue]Dragon Ball Super - 1x14 - ¡El último esfuerzo! ¡La batalla de los Dioses concluye![/COLOR]</title>        
<urlsolve></urlsolve>
<thumbnail></thumbnail>
<fanart></fanart>
</item>